odoo9_addon_server_environment_ir_config_parameter-9.0.1.0.0.99.dev10-py2.7-nspkg.pth
odoo9_addon_server_environment_ir_config_parameter-9.0.1.0.0.99.dev10.dist-info/DESCRIPTION.rst
odoo9_addon_server_environment_ir_config_parameter-9.0.1.0.0.99.dev10.dist-info/METADATA
odoo9_addon_server_environment_ir_config_parameter-9.0.1.0.0.99.dev10.dist-info/RECORD
odoo9_addon_server_environment_ir_config_parameter-9.0.1.0.0.99.dev10.dist-info/WHEEL
odoo9_addon_server_environment_ir_config_parameter-9.0.1.0.0.99.dev10.dist-info/metadata.json
odoo9_addon_server_environment_ir_config_parameter-9.0.1.0.0.99.dev10.dist-info/namespace_packages.txt
odoo9_addon_server_environment_ir_config_parameter-9.0.1.0.0.99.dev10.dist-info/top_level.txt
odoo_addons/server_environment_ir_config_parameter/README.rst
odoo_addons/server_environment_ir_config_parameter/__init__.py
odoo_addons/server_environment_ir_config_parameter/__openerp__.py
odoo_addons/server_environment_ir_config_parameter/i18n/ca.po
odoo_addons/server_environment_ir_config_parameter/i18n/de.po
odoo_addons/server_environment_ir_config_parameter/i18n/es.po
odoo_addons/server_environment_ir_config_parameter/i18n/hr.po
odoo_addons/server_environment_ir_config_parameter/i18n/server_environment_ir_config_parameter.pot
odoo_addons/server_environment_ir_config_parameter/models/__init__.py
odoo_addons/server_environment_ir_config_parameter/models/ir_config_parameter.py
odoo_addons/server_environment_ir_config_parameter/static/description/icon.png
odoo_addons/server_environment_ir_config_parameter/tests/__init__.py
odoo_addons/server_environment_ir_config_parameter/tests/test_server_environment_ircp.py
